textbasedlib/__init__.py
textbasedlib/plugin_manager.py
textbasedlib/tblib.py
textbasedlib-1.2.dist-info/LICENSE
textbasedlib-1.2.dist-info/METADATA
textbasedlib-1.2.dist-info/WHEEL
textbasedlib-1.2.dist-info/top_level.txt
textbasedlib-1.2.dist-info/RECORD
